{
  "folder": "NMOyIu5qPUNyp5tk",
  "name": "NEX 40% - Técnica Secreta",
  "type": "ability",
  "_id": "9irHQDehCDbuLWxa",
  "img": "systems/ordemparanormal/media/icons/abilities/class/fighter/Aniquilador/Tecnica_Secreta.svg",
  "system": {
    "id": 0,
    "abilityType": "path",
    "preRequisite": "",
    "description": "<p>A categoria da arma favorita passa a ser reduzida em II. Quando faz um ataque com ela, voc&ecirc; pode gastar 2 PE para executar um dos efeitos abaixo como parte do ataque. Voc&ecirc; pode adicionar mais efeitos gastando +2 PE por efeito adicional.</p>\n<ul>\n<li><strong>Amplo.</strong> O ataque pode atingir um alvo adicional em seu alcance e adjacente ao original (use o mesmo teste de ataque para ambos).</li>\n<li><strong>Destruidor.</strong> Aumenta o multiplicador de cr&iacute;tico da arma em +1.</li>\n</ul>"
  },
  "effects": [],
  "sort": 0,
  "ownership": {
    "default": 0,
    "D087Zkcpssj33iAO": 3
  },
  "flags": {},
  "_stats": {
    "systemId": "ordemparanormal",
    "systemVersion": "6.5.0",
    "coreVersion": "11.315",
    "createdTime": 1712181278887,
    "modifiedTime": 1712188260661,
    "lastModifiedBy": "D087Zkcpssj33iAO"
  },
  "_key": "!items!9irHQDehCDbuLWxa"
}
